avisengine_pkg/__init__.py
avisengine_pkg/utils.py
avisengine-2.0.1.dist-info/METADATA
avisengine-2.0.1.dist-info/WHEEL
avisengine-2.0.1.dist-info/top_level.txt
avisengine-2.0.1.dist-info/RECORD
