Metadata-Version: 2.4
Name: avisengine
Version: 2.0.1
Summary: Python API for AVIS Engine Simulator
Home-page: 
Author: AVIS Engine
Author-email: 
Classifier: Programming Language :: Python :: 3
Classifier: License :: OSI Approved :: MIT License
Classifier: Operating System :: OS Independent
Requires-Python: >=3.6
Requires-Dist: numpy>=1.18.3
Requires-Dist: opencv-contrib-python>=4.2.0.34
Requires-Dist: opencv-python>=4.2.0.34
Requires-Dist: Pillow>=7.1.2
Requires-Dist: PySocks>=1.7.1
Requires-Dist: PyYAML>=5.3.1
Requires-Dist: regex>=2020.4.4
Requires-Dist: requests>=2.22.0
Dynamic: author
Dynamic: classifier
Dynamic: description
Dynamic: description-content-type
Dynamic: requires-dist
Dynamic: requires-python
Dynamic: summary
